blog/__init__.py
blog/__main__.py
blog/_blog.py
blog/trello_to_markdown.py
blog/utils.py
blog/version.py
blog/meta_files/__init__.py
blog/meta_files/model.py
blog/theme/__init__.py
blog/trello/__init__.py
blog/trello/controller.py
blog/trello/model.py
blog/trello/view.py
blog-1.0.1.dist-info/LICENSE
blog-1.0.1.dist-info/METADATA
blog-1.0.1.dist-info/WHEEL
blog-1.0.1.dist-info/entry_points.txt
blog-1.0.1.dist-info/top_level.txt
blog-1.0.1.dist-info/RECORD
