Metadata-Version: 2.1
Name: blog
Version: 1.0.1
Summary: A static website generator
Home-page: https://github.com/tomleo/blog
Author: Tom Leo
Author-email: tom@tomleo.com
License: UNKNOWN
Project-URL: Bug Reports, https://github.com/tomleo/blog/issues
Project-URL: Funding, https://donate.pypi.org
Project-URL: Source, https://github.com/tomleo/blog/
Keywords: static website generator
Platform: UNKNOWN
Classifier: Development Status :: 3 - Alpha
Classifier: Environment :: Console
Classifier: Environment :: Web Environment
Classifier: Intended Audience :: Developers
Classifier: License :: OSI Approved :: GNU General Public License v3 (GPLv3)
Classifier: Natural Language :: English
Classifier: Operating System :: OS Independent
Classifier: Programming Language :: Python :: 3.7
Classifier: Programming Language :: Python :: Implementation :: CPython
Classifier: Topic :: Internet
Classifier: Topic :: Software Development :: Build Tools
Classifier: Topic :: Utilities
Classifier: Typing :: Typed
Requires-Python: >=3.7.*
Provides-Extra: dev
Provides-Extra: test
